intype/__init__.py
intype/literal.py
intype/numeric.py
intype-0.0.3.dist-info/WHEEL
intype-0.0.3.dist-info/METADATA
intype-0.0.3.dist-info/RECORD
